xrag/__init__.py
xrag/cli.py
xrag/config.py
xrag/default_config.toml
xrag/api/__init__.py
xrag/api/server.py
xrag/data/__init__.py
xrag/data/qa_loader.py
xrag/embs/__init__.py
xrag/embs/chatglmemb.py
xrag/embs/embedding.py
xrag/eval/DeepEvalLocalModel.py
xrag/eval/EvalModelAgent.py
xrag/eval/__init__.py
xrag/eval/evaluate_LLM.py
xrag/eval/evaluate_TGT.py
xrag/eval/evaluate_TRT.py
xrag/eval/evaluate_rag.py
xrag/index/__init__.py
xrag/index/index.py
xrag/launcher/__init__.py
xrag/launcher/launch.py
xrag/llms/__init__.py
xrag/llms/chatglm4.py
xrag/llms/huggingface_model.py
xrag/llms/llm.py
xrag/process/__init__.py
xrag/process/postprocess_rerank.py
xrag/process/postprocessor.py
xrag/process/query_transform.py
xrag/retrievers/__init__.py
xrag/retrievers/retriever.py
xrag/webui/__init__.py
xrag/webui/app.py
xrag/webui/run.py
examinationrag-0.1.4.dist-info/LICENSE
examinationrag-0.1.4.dist-info/METADATA
examinationrag-0.1.4.dist-info/WHEEL
examinationrag-0.1.4.dist-info/entry_points.txt
examinationrag-0.1.4.dist-info/top_level.txt
examinationrag-0.1.4.dist-info/RECORD
