Metadata-Version: 2.2
Name: examinationrag
Version: 0.1.4
Summary: XRAG: eXamining the Core - Benchmarking Foundational Component Modules in Advanced Retrieval-Augmented Generation
Home-page: https://github.com/DocAILab/XRAG
Author: DocAILab
Author-email: luoyangyifei@buaa.edu.cn
License: Apache 2.0 License
Keywords: RAG,LLM,ChatGPT,LLamaIndex,Benchmarking
Classifier: Development Status :: 4 - Beta
Classifier: Intended Audience :: Developers
Classifier: Intended Audience :: Education
Classifier: Intended Audience :: Science/Research
Classifier: License :: OSI Approved :: Apache Software License
Classifier: Operating System :: OS Independent
Classifier: Programming Language :: Python :: 3
Classifier: Programming Language :: Python :: 3.9
Classifier: Programming Language :: Python :: 3.10
Classifier: Programming Language :: Python :: 3.11
Classifier: Topic :: Scientific/Engineering :: Artificial Intelligence
Requires-Python: >=3.9.0
License-File: LICENSE
Requires-Dist: dashscope==1.20.0
Requires-Dist: langchain==0.2.7
Requires-Dist: scikit-learn==1.3.2
Requires-Dist: llama-index==0.11.11
Requires-Dist: litellm==1.48.10
Requires-Dist: numpy==1.26.4
Requires-Dist: openai==1.47.0
Requires-Dist: pandas==2.2.2
Requires-Dist: sentence_transformers==3.0.1
Requires-Dist: torch==2.3.0
Requires-Dist: tqdm==4.66.4
Requires-Dist: transformers==4.42.2
Requires-Dist: llama-index-embeddings-huggingface==0.3.1
Requires-Dist: llama-index-embeddings-langchain==0.2.1
Requires-Dist: llama-index-embeddings-openai==0.2.5
Requires-Dist: llama-index-retrievers-bm25==0.3.0
Requires-Dist: llama-index-readers-file==0.2.2
Requires-Dist: llama-index-legacy==0.9.48
Requires-Dist: llama-index-llms-dashscope==0.2.1
Requires-Dist: llama-index-llms-huggingface==0.3.4
Requires-Dist: llama-index-llms-openai==0.2.9
Requires-Dist: llama-index-llms-ollama==0.3.0
Requires-Dist: FlagEmbedding==1.2.10
Requires-Dist: zhipuai
Requires-Dist: uptrain
Requires-Dist: toml
Requires-Dist: deepeval==0.21.26
Requires-Dist: rouge-score==0.0.4
Requires-Dist: evaluate
Requires-Dist: fire>=0.4.0
Requires-Dist: validators
Requires-Dist: llama-index-postprocessor-cohere-rerank==0.2.1
Requires-Dist: llama-index-postprocessor-colbert-rerank==0.2.1
Requires-Dist: llama-index-postprocessor-flag-embedding-reranker==0.2.0
Requires-Dist: sacrebleu
Requires-Dist: jiwer
Requires-Dist: seqeval==1.2.2
Requires-Dist: bert_score
Requires-Dist: sentencepiece
Requires-Dist: mauve-text
Requires-Dist: streamlit
Requires-Dist: streamlit-option-menu
Requires-Dist: streamlit_card
Requires-Dist: fastapi
Requires-Dist: uvicorn
Requires-Dist: pydantic
Provides-Extra: jury
Requires-Dist: jury; extra == "jury"
Dynamic: author
Dynamic: author-email
Dynamic: classifier
Dynamic: description
Dynamic: description-content-type
Dynamic: home-page
Dynamic: keywords
Dynamic: license
Dynamic: provides-extra
Dynamic: requires-dist
Dynamic: requires-python
Dynamic: summary
